skgrf/__init__.py
skgrf/_version.py
skgrf/base.py
skgrf/ensemble/__init__.py
skgrf/ensemble/base.py
skgrf/ensemble/boosted_regressor.py
skgrf/ensemble/causal_regressor.py
skgrf/ensemble/classifier.py
skgrf/ensemble/instrumental_regressor.py
skgrf/ensemble/local_linear_regressor.py
skgrf/ensemble/quantile_regressor.py
skgrf/ensemble/regressor.py
skgrf/ensemble/survival.py
skgrf/grf/.gitignore
skgrf/grf/CMakeLists.txt
skgrf/grf/COPYING
skgrf/grf/README.md
skgrf/grf/REFERENCE.md
skgrf/grf/src/.gitignore
skgrf/grf/src/analysis/SplitFrequencyComputer.cpp
skgrf/grf/src/analysis/SplitFrequencyComputer.h
skgrf/grf/src/commons/Data.cpp
skgrf/grf/src/commons/Data.h
skgrf/grf/src/commons/globals.h
skgrf/grf/src/commons/utility.cpp
skgrf/grf/src/commons/utility.h
skgrf/grf/src/forest/Forest.cpp
skgrf/grf/src/forest/Forest.h
skgrf/grf/src/forest/ForestOptions.cpp
skgrf/grf/src/forest/ForestOptions.h
skgrf/grf/src/forest/ForestPredictor.cpp
skgrf/grf/src/forest/ForestPredictor.h
skgrf/grf/src/forest/ForestPredictors.cpp
skgrf/grf/src/forest/ForestPredictors.h
skgrf/grf/src/forest/ForestTrainer.cpp
skgrf/grf/src/forest/ForestTrainer.h
skgrf/grf/src/forest/ForestTrainers.cpp
skgrf/grf/src/forest/ForestTrainers.h
skgrf/grf/src/prediction/CausalSurvivalPredictionStrategy.cpp
skgrf/grf/src/prediction/CausalSurvivalPredictionStrategy.h
skgrf/grf/src/prediction/DefaultPredictionStrategy.h
skgrf/grf/src/prediction/InstrumentalPredictionStrategy.cpp
skgrf/grf/src/prediction/InstrumentalPredictionStrategy.h
skgrf/grf/src/prediction/LLCausalPredictionStrategy.cpp
skgrf/grf/src/prediction/LLCausalPredictionStrategy.h
skgrf/grf/src/prediction/LocalLinearPredictionStrategy.cpp
skgrf/grf/src/prediction/LocalLinearPredictionStrategy.h
skgrf/grf/src/prediction/MultiCausalPredictionStrategy.cpp
skgrf/grf/src/prediction/MultiCausalPredictionStrategy.h
skgrf/grf/src/prediction/MultiRegressionPredictionStrategy.cpp
skgrf/grf/src/prediction/MultiRegressionPredictionStrategy.h
skgrf-0.3.0.dist-info/LICENSE.txt
skgrf-0.3.0.dist-info/WHEEL
skgrf-0.3.0.dist-info/METADATA
skgrf-0.3.0.dist-info/RECORD
