Metadata-Version: 2.1
Name: skgrf
Version: 0.3.0
Summary: python bindings for C++ generalized random forests (grf)
Home-page: https://github.com/crflynn/skgrf
License: GPL-3.0-or-later
Keywords: generalized,random,forest,machine,learning
Author: flynn
Author-email: crf204@gmail.com
Requires-Python: >=3.7,<4.0
Classifier: Development Status :: 4 - Beta
Classifier: Intended Audience :: Science/Research
Classifier: License :: OSI Approved :: GNU General Public License v3 (GPLv3)
Classifier: License :: OSI Approved :: GNU General Public License v3 or later (GPLv3+)
Classifier: Programming Language :: C++
Classifier: Programming Language :: Python
Classifier: Programming Language :: Python :: 3
Classifier: Programming Language :: Python :: 3.10
Classifier: Programming Language :: Python :: 3.7
Classifier: Programming Language :: Python :: 3.8
Classifier: Programming Language :: Python :: 3.9
Classifier: Topic :: Scientific/Engineering
Requires-Dist: scikit-learn (>=0.23.0,<1.0)
Project-URL: Documentation, https://github.com/crflynn/skgrf
Project-URL: Repository, https://github.com/crflynn/skgrf
